boltons-stubs/METADATA.toml
boltons-stubs/__init__.pyi
boltons-stubs/cacheutils.pyi
boltons-stubs/debugutils.pyi
boltons-stubs/deprutils.pyi
boltons-stubs/dictutils.pyi
boltons-stubs/easterutils.pyi
boltons-stubs/ecoutils.pyi
boltons-stubs/excutils.pyi
boltons-stubs/fileutils.pyi
boltons-stubs/formatutils.pyi
boltons-stubs/funcutils.pyi
boltons-stubs/gcutils.pyi
boltons-stubs/ioutils.pyi
boltons-stubs/iterutils.pyi
boltons-stubs/jsonutils.pyi
boltons-stubs/listutils.pyi
boltons-stubs/mathutils.pyi
boltons-stubs/mboxutils.pyi
boltons-stubs/namedutils.pyi
boltons-stubs/pathutils.pyi
boltons-stubs/py.typed
boltons-stubs/queueutils.pyi
boltons-stubs/setutils.pyi
boltons-stubs/socketutils.pyi
boltons-stubs/statsutils.pyi
boltons-stubs/strutils.pyi
boltons-stubs/tableutils.pyi
boltons-stubs/tbutils.pyi
boltons-stubs/timeutils.pyi
boltons-stubs/typeutils.pyi
boltons-stubs/urlutils.pyi
types_boltons-25.0.0.20250822.dist-info/licenses/LICENSE
types_boltons-25.0.0.20250822.dist-info/METADATA
types_boltons-25.0.0.20250822.dist-info/WHEEL
types_boltons-25.0.0.20250822.dist-info/top_level.txt
types_boltons-25.0.0.20250822.dist-info/RECORD
